ofxstatement_japan/__init__.py
ofxstatement_japan/prestia.py
ofxstatement_japan-0.0.1.dist-info/METADATA
ofxstatement_japan-0.0.1.dist-info/WHEEL
ofxstatement_japan-0.0.1.dist-info/entry_points.txt
ofxstatement_japan-0.0.1.dist-info/top_level.txt
ofxstatement_japan-0.0.1.dist-info/RECORD
