Metadata-Version: 2.4
Name: ofxstatement-japan
Version: 0.0.1
Summary: OFXStatement plugins for Japanese banks
Author-email: Alexandre Bourquelot <elrandar@users.noreply.github.com>
Project-URL: Homepage, https://github.com/elrandar/ofxstatement-japan
Project-URL: Repository, https://github.com/elrandar/ofxstatement-japan
Project-URL: Issues, https://github.com/elrandar/ofxstatement-japan/issues
Keywords: ofx,banking,statement,plugin,ofxstatement,prestia,japan,smbc
Classifier: Development Status :: 3 - Alpha
Classifier: Programming Language :: Python :: 3
Classifier: Natural Language :: English
Classifier: Topic :: Office/Business :: Financial :: Accounting
Classifier: Topic :: Utilities
Classifier: Environment :: Console
Classifier: Operating System :: OS Independent
Classifier: License :: OSI Approved :: GNU General Public License v3 (GPLv3)
Requires-Python: >=3.0
Requires-Dist: ofxstatement
